scriptnorm/__init__.py
scriptnorm/constants.py
scriptnorm/normalization.py
scriptnorm-4.0.dist-info/METADATA
scriptnorm-4.0.dist-info/WHEEL
scriptnorm-4.0.dist-info/top_level.txt
scriptnorm-4.0.dist-info/RECORD
