Metadata-Version: 2.1
Name: scriptnorm
Version: 4.0
Summary: A library for text normalization for a set of languages
Home-page: https://github.com/rnd2110/SCRIPTS_Normalization
Author: Ramy Eskander
Author-email: rnd2110@columbia.edu
License: UNKNOWN
Platform: UNKNOWN
Classifier: Programming Language :: Python :: 3
Classifier: License :: OSI Approved :: MIT License
Classifier: Operating System :: OS Independent
